unicode_age/__init__.py
unicode_age/unicode_age_db.py
unicode_age-17.0.0.0.dist-info/licenses/LICENSE
unicode_age-17.0.0.0.dist-info/METADATA
unicode_age-17.0.0.0.dist-info/WHEEL
unicode_age-17.0.0.0.dist-info/top_level.txt
unicode_age-17.0.0.0.dist-info/RECORD
