Metadata-Version: 2.4
Name: unicode_age
Version: 17.0.0.0
Summary: A package for determining what version a Unicode codepoint was added to the standard
License: MIT
Requires-Python: >=3.8
License-File: LICENSE
Provides-Extra: dev
Requires-Dist: pytest; extra == "dev"
Requires-Dist: twine; extra == "dev"
Requires-Dist: build; extra == "dev"
Dynamic: license-file
